orbitalis/__init__.py
orbitalis/core/__init__.py
orbitalis/core/core.py
orbitalis/core/requirement.py
orbitalis/core/sink.py
orbitalis/core/state.py
orbitalis/events/__init__.py
orbitalis/events/close_connection.py
orbitalis/events/discover.py
orbitalis/events/keepalive.py
orbitalis/events/offer.py
orbitalis/events/reply.py
orbitalis/events/response.py
orbitalis/orbiter/__init__.py
orbitalis/orbiter/connection.py
orbitalis/orbiter/orbiter.py
orbitalis/orbiter/pending_request.py
orbitalis/orbiter/schemaspec.py
orbitalis/plugin/__init__.py
orbitalis/plugin/operation.py
orbitalis/plugin/plugin.py
orbitalis/plugin/state.py
orbitalis/state_machine/__init__.py
orbitalis/state_machine/state_machine.py
orbitalis/utils/__init__.py
orbitalis/utils/allowblocklist.py
orbitalis/utils/task.py
orbitalis-1.1.4.dist-info/licenses/LICENSE
orbitalis-1.1.4.dist-info/METADATA
orbitalis-1.1.4.dist-info/WHEEL
orbitalis-1.1.4.dist-info/top_level.txt
orbitalis-1.1.4.dist-info/RECORD
