Metadata-Version: 2.4
Name: orbitalis
Version: 1.1.4
Summary: Event-driven micro-kernel for Python
Author: Marco Picone
Author-email: Nicola Ricciardi <ricciardincl@gmail.com>
Project-URL: Homepage, https://github.com/nricciardi/orbitalis
Project-URL: Issues, https://github.com/nricciardi/orbitalis/issues
Classifier: Programming Language :: Python :: 3
Classifier: License :: OSI Approved :: MIT License
Classifier: Operating System :: OS Independent
Requires-Python: >=3.12
License-File: LICENSE
Requires-Dist: busline>=1.2.0
Dynamic: license-file
